mkdocs_exclude_notused/__init__.py
mkdocs_exclude_notused/plugin.py
mkdocs_exclude_notused-1.5.0.dist-info/LICENSE
mkdocs_exclude_notused-1.5.0.dist-info/METADATA
mkdocs_exclude_notused-1.5.0.dist-info/WHEEL
mkdocs_exclude_notused-1.5.0.dist-info/entry_points.txt
mkdocs_exclude_notused-1.5.0.dist-info/top_level.txt
mkdocs_exclude_notused-1.5.0.dist-info/RECORD
