Metadata-Version: 2.1
Name: mkdocs_exclude_notused
Version: 1.5.0
Summary: Simple plugin to exclude notused .md files from docs folder
Home-page: https://github.com/michal2612/mkdocs-exclude-notused
Author: Michal Domanski
License: MIT
License-File: LICENSE
Requires-Dist: mkdocs
